Magma/__init__.py
Magma_Indonesia_API-2.0.3.dist-info/LICENSE.txt
Magma_Indonesia_API-2.0.3.dist-info/METADATA
Magma_Indonesia_API-2.0.3.dist-info/WHEEL
Magma_Indonesia_API-2.0.3.dist-info/top_level.txt
Magma_Indonesia_API-2.0.3.dist-info/RECORD
